kliffHenger/__init__.py
kliffHenger/main.py
kliffHenger-0.0.1.dist-info/METADATA
kliffHenger-0.0.1.dist-info/WHEEL
kliffHenger-0.0.1.dist-info/top_level.txt
kliffHenger-0.0.1.dist-info/RECORD
